a2a_sigstore/__init__.py
a2a_sigstore/provenance.py
a2a_sigstore/signer.py
a2a_sigstore/verifier.py
a2a_sigstore/cli/__init__.py
a2a_sigstore/cli/main.py
a2a_sigstore/cli/serve.py
a2a_sigstore/cli/sign.py
a2a_sigstore/cli/verify.py
a2a_sigstore/models/__init__.py
a2a_sigstore/models/agent_card.py
a2a_sigstore/models/provenance.py
a2a_sigstore/models/signature.py
a2a_sigstore/utils/__init__.py
a2a_sigstore/utils/ci.py
a2a_sigstore/utils/crypto.py
a2a_sigstore-0.4.0.dist-info/METADATA
a2a_sigstore-0.4.0.dist-info/WHEEL
a2a_sigstore-0.4.0.dist-info/entry_points.txt
a2a_sigstore-0.4.0.dist-info/RECORD
