Metadata-Version: 2.4
Name: a2a-sigstore
Version: 0.4.0
Summary: Keyless signing library for A2A Agent Cards using Sigstore and SLSA provenance
Author-email: Luke Hinds <luke@rdrocket.com>
Requires-Python: >=3.11
Requires-Dist: a2a-sdk>=0.2.16
Requires-Dist: betterproto>=2.0.0b6
Requires-Dist: click>=8.0.0
Requires-Dist: cryptography>=41.0.0
Requires-Dist: fastapi>=0.100.0
Requires-Dist: httpx>=0.24.0
Requires-Dist: pydantic<3.0.0,>=2.0.0
Requires-Dist: rich>=13.0.0
Requires-Dist: sigstore>=3.6.4
Requires-Dist: uvicorn>=0.23.0
